README.rst
setup.py
sum_wzl.egg-info/PKG-INFO
sum_wzl.egg-info/SOURCES.txt
sum_wzl.egg-info/dependency_links.txt
sum_wzl.egg-info/top_level.txt
wzl_sum/__init__.py
wzl_sum/sum.py