Metadata-Version: 1.0
Name: sum-wzl
Version: 0.2
Summary: find the sum from begin number to end number, end number included
Home-page: UNKNOWN
Author: wangzhaoliang
Author-email: sa516326@mail.ustc.edu.cn
License: Apache
Platform: UNKNOWN
